alibabacloud_appstream_center20210901/__init__.py
alibabacloud_appstream_center20210901/client.py
alibabacloud_appstream_center20210901/models/__init__.py
alibabacloud_appstream_center20210901/models/_approve_ota_task_request.py
alibabacloud_appstream_center20210901/models/_approve_ota_task_response.py
alibabacloud_appstream_center20210901/models/_approve_ota_task_response_body.py
alibabacloud_appstream_center20210901/models/_authorize_instance_group_request.py
alibabacloud_appstream_center20210901/models/_authorize_instance_group_response.py
alibabacloud_appstream_center20210901/models/_authorize_instance_group_response_body.py
alibabacloud_appstream_center20210901/models/_authorize_instance_group_shrink_request.py
alibabacloud_appstream_center20210901/models/_create_app_instance_group_request.py
alibabacloud_appstream_center20210901/models/_create_app_instance_group_response.py
alibabacloud_appstream_center20210901/models/_create_app_instance_group_response_body.py
alibabacloud_appstream_center20210901/models/_create_app_instance_group_shrink_request.py
alibabacloud_appstream_center20210901/models/_create_image_by_instance_request.py
alibabacloud_appstream_center20210901/models/_create_image_by_instance_response.py
alibabacloud_appstream_center20210901/models/_create_image_by_instance_response_body.py
alibabacloud_appstream_center20210901/models/_create_image_from_app_instance_group_request.py
alibabacloud_appstream_center20210901/models/_create_image_from_app_instance_group_response.py
alibabacloud_appstream_center20210901/models/_create_image_from_app_instance_group_response_body.py
alibabacloud_appstream_center20210901/models/_create_wuying_server_request.py
alibabacloud_appstream_center20210901/models/_create_wuying_server_response.py
alibabacloud_appstream_center20210901/models/_create_wuying_server_response_body.py
alibabacloud_appstream_center20210901/models/_delete_app_instance_group_request.py
alibabacloud_appstream_center20210901-4.7.6.dist-info/LICENSE
alibabacloud_appstream_center20210901-4.7.6.dist-info/METADATA
alibabacloud_appstream_center20210901-4.7.6.dist-info/WHEEL
alibabacloud_appstream_center20210901-4.7.6.dist-info/top_level.txt
alibabacloud_appstream_center20210901-4.7.6.dist-info/RECORD
